{"खासै": 1, "अचम्म": 1, "होइन": 14, "बस्": 1, "भिडि": 1, "हनुमान": 1, "जत्था": 1, "बबुरासितै": 1, "कुम": 1, "मिलाउन": 1, "आउने": 2, "हुन्": 12, "भन्ने": 16, "सम्झेर": 1, "वाक्क": 1, "प्रचण्ड": 10, "छलाङ": 1, "अपेक्षित": 1, "हित": 1, "हुनेछ": 1, "राजनीतिक": 6, "दम्भ": 2, "पुरै": 1, "अन्धो": 2, "भएर": 1, "हुस्सु": 1, "काग": 1, "निकास": 2, "दिए": 2, "जाति": 2, "सबै": 17, "मन्त्री": 8, "डाक्नु": 1, "स्रोत": 1, "भन्यो": 4, "मन्त्रिपरिषद्बाट": 1, "दिने": 3, "निर्णय": 3, "हुन": 8, "सक्छ": 4, "स्रोत–साधन": 1, "कब्जा": 1, "गर्ने": 15, "प्रदेश": 1, "स्थानीय": 3, "बनाउने": 4, "षड्यन्त्र": 3, "लागे": 2, "सरकार": 41, "आफैं": 2, "सिंहदरबार": 2, "राज्यस्रोत": 1, "दोहन": 2, "अपराधी": 2, "चरित्र": 1, "जुन": 1, "त्यही": 2, "प्रस्टिए": 1, "प्रमुख": 4, "किसान": 3, "पोखे": 1, "प्रायोजित": 2, "भन्दै": 3, "राख्न": 3, "पैसा": 1, "राख्ने": 1, "ट्याङ्": 1, "गरिदेउ": 1, "भने": 26, "थिएनन्": 2, "संकट": 4, "उत्पादन": 2, "बजार": 2, "पुर्याउने": 1, "जिम्मेवारी": 4, "आफ्नो": 7, "केहिपनी": 1, "नदेख्नु": 1, "कस्तो": 5, "दिन": 10, "नमस्कार": 2, "प्रतिक्रिया": 1, "अपेक्षा": 2, "गर्नुभए": 2, "रहेछ": 4, "गहन": 1, "यथार्थता": 1, "कलम": 2, "चलाउनु": 1, "कुरा": 25, "बिद्रोह": 1, "अगाडी": 2, "लेख्दा": 1, "थोरै": 1, "सब्द": 2, "धेरै": 3, "कोसिस": 1, "गर्नु": 9, "होला": 9, "धन्यवाद": 3, "स्वास्थ्य": 3, "खरिद": 2, "कानुनी": 1, "बढ्यो": 1, "अनियमितता": 1, "हेर्ने": 3, "रोग": 4, "गर्न": 10, "चाहन्छु": 1, "कर्म": 1, "कथा": 4, "कथ्ने": 1, "प्रत्येक": 2, "चुनौती": 1, "चाहन्छौं": 1, "प्रधानमन्त्री": 10, "इश्वर": 2, "पोखरेल": 1, "सेतोपाटि": 2, "अन्तर्वार्ता": 2, "सुशासन": 1, "बर्दिया": 1, "जान": 6, "गोपालसिंह": 1, "परियार": 1, "रुँदै": 1, "पठाइदेऊ": 1, "बसे": 4, "पाल": 1, "पानी": 3, "सकियाे": 1, "देख्ने": 2, "बोल्ने": 1, "लेख्ने": 1, "अधिकार": 2, "निहित": 1, "रहे": 4, "औपचारिक": 1, "यतिबेला": 1, "छौं": 2, "मातृभूमि": 1, "पाउँ": 1, "समाधान": 1, "होइनन्": 2, "गरेर": 5, "काम": 9, "विचलित": 1, "हुनु": 12, "कुन": 5, "योग्यता": 1, "नेता": 7, "यिनि": 2, "राजनीति": 9, "थाहा": 4, "उस्ता": 1, "टिम": 1, "उस्तै": 1, "हेर्नुस्": 2, "साशक": 2, "रुप": 3, "यहाँ": 4, "रूँदैछ": 3, "हिँड्न": 2, "नपाएर": 1, "मान्छे": 8, "गर्नुहुन्छ": 1, "उपप्रधानमन्त्री": 2, "पोखरा": 1, "गिरे": 1, "नालायक": 3, "अनि": 4, "सामन्ती": 3, "भन्छ": 1, "ओम्नीलाई‌": 1, "भुक्तानी": 1, "‌दिन": 1, "ईश्वर": 1, "‌पोखरेलसम्मको‌": 1, "परे": 6, "ओम्नी": 2, "सामानवापत": 1, "करोड": 2, "दाबीसहित": 1, "पत्र‌": 1, "मा‌": 1, "पठाए": 1, "हप्तौँ": 1, "हिँडेरै": 1, "पुगे": 1, "बाटो": 5, "अलपत्र": 3, "परेका": 1, "तिनलाई": 1, "खुवाउने": 1, "नागरिक": 10, "मद्दत": 1, "बताउने": 1, "पत्रकार": 2, "आदेश": 4, "अदालत": 2, "परिचालित": 1, "तिन": 4, "आवाज": 2, "कर्कश": 1, "ध्वनि": 1, "ठान्ने": 1, "कान": 2, "परीक्षण": 2, "गराउन": 1, "उपयुक्त": 1, "जहाँ": 3, "चाहिए": 2, "त्यहाँ": 1, "उपस्थिति": 1, "छैन": 22, "भाइरस": 1, "नियन्त्रण": 1, "अग्रमोर्चा": 1, "खटिए": 1, "डाक्टर": 11, "हतोत्साहित": 1, "आपत्काल": 1, "बहाना": 1, "शक्ति": 1, "दुरुपयोग": 2, "पुलिस": 2, "स्टेट’": 1, "अनुभूति": 1, "दिलाउन": 1, "बलशाली": 1, "देखिँदै": 1, "सिधै": 1, "भन्न": 4, "नसके": 1, "खोजे": 1, "पत्रकारिता": 2, "किन": 17, "चाहियो": 4, "शासन": 5, "बिन्ती": 1, "चडाउनु": 1, "भनी": 1, "लेखिए": 3, "मिडिया": 1, "नआउनु": 1, "सिद्धान्त": 1, "उत्तर": 1, "कोरिया": 1, "पुगि": 1, "हौँ": 1, "बचाउन": 2, "घस्रिँदै": 1, "कान्तिपुर": 3, "गर्दैन": 1, "गर्छ": 3, "अवश्य": 1, "पूर्वाग्रह": 1, "दुराशय": 1, "नभए": 3, "सही": 1, "जन्माउने": 1, "झन्": 2, "दुई": 1, "कोरोना": 17, "विशेषज्ञ": 3, "पुन": 4, "कुरो": 3, "लगभग": 1, "सकियो": 2, "ट्रिपल": 1, "अनुपम": 1, "भाइरसविद्": 1, "केही": 12, "कमी": 1, "सुखद्": 1, "यथार्थ": 3, "यस्तो": 3, "भाइरसविरुद्ध": 2, "लडाइँ": 1, "सिङ्गल": 1, "खाँचो": 1, "#खगेन्द्र": 1, "संकटकालीन": 1, "जोहो": 1, "नीति": 1, "बरु": 2, "आनन्द": 1, "स्वस्थ": 2, "मनपसन्द’": 1, "तालिका": 1, "निष्कर्ष": 1, "यही": 1, "निस्कन्छ": 1, "गरिब": 11, "सरोकार": 1, "कोसौं": 1, "मग्नमस्त": 1, "अन्न": 1, "सम्पादकीय": 1, "जतिसु": 1, "रुचि": 1, "सन्देश": 2, "प्रवाहित": 1, "दुर्भाग्य": 1, "निर्वाचन": 5, "विकास": 5, "कार्यक्रम’को": 1, "बजेट": 3, "कटौतीविरुद्घ": 1, "उभिनु": 1, "निर्दयी": 3, "चरित्र’": 1, "प्रदर्शन": 1, "फर्": 2, "सम्झिन": 1, "वाक्य": 1, "नेताका": 1, "चलायमान": 2, "कर्पाेरेट": 2, "हाउस": 2, "कृष्ण": 10, "सम्पादक": 1, "नेकपा": 8, "कुसल": 1, "अप्रेसन": 1, "राजमार्गको": 1, "कारुणिक": 3, "नेपाल": 6, "कम्युनिस्ट": 4, "आन्दोलन": 3, "यति": 3, "कठोर": 1, "कसरी": 6, "पुग्यो": 1, "पंक्ति": 1, "त्यस": 8, "समिक्षा": 3, "सायद": 6, "बचाउने": 1, "जोगी": 1, "खुवाउँदै": 1, "बसपार्क": 1, "देशसञ्चार": 1, "अन्त्य": 1, "पैदलयात्री": 2, "माफ": 2, "गरिदिनुस्": 1, "प्रतिपक्षी": 1, "दललाई": 1, "कलंक": 1, "सिंगो": 1, "पार्टी": 9, "प्रतिरक्षात्मक": 1, "बनाए": 4, "संवैधानिक": 1, "निकाय": 1, "आफ्नै": 2, "टिकट": 1, "फाइदा": 2, "लागि": 7, "उभिन्छन्": 1, "शासक": 2, "परीक्षा": 2, "छैनन्": 4, "शासित": 1, "लिन": 1, "प्रतिबद्ध": 1, "गरी": 4, "पुग्नु": 1, "समय": 5, "बालिदिनुहोला": 1, "गान": 1, "गाइदिनुहोला": 1, "अरू": 4, "कसै": 5, "नक्कल": 1, "नयाँ": 4, "आउन": 2, "सक्छन्": 1, "विनम्रता": 1, "पालन": 1, "गरिदिनुहोला": 1, "अभियन्ता": 1, "पुरस्कृत": 3, "हुने": 8, "मन्त्रालय": 1, "गलत": 1, "प्रवचन": 1, "तोकिसके": 1, "लकडाउन": 5, "बस्नुपथ्र्यो": 1, "समस्या": 5, "चुक्यो": 1, "गर्‍यो": 2, "एसिया": 1, "ठूलो": 1, "बन्यो": 1, "यतिखेर": 1, "नपाए": 1, "चाहिन्छ": 2, "कता–कता": 2, "लाग्छ": 3, "संविधान": 2, "केबल": 1, "परीक्षार्थी": 1, "लाग्नेछ": 1, "लोकतन्त्र": 1, "हुनुहुन्छ": 1, "तन्त्र": 2, "फरक": 2, "हरेक": 3, "संगठन": 2, "स्ववियु": 1, "चुनाव": 7, "जित्ने": 1, "क्याम्पस": 1, "हप्ता": 1, "उठाउने": 1, "लक्ष्य": 2, "कवि": 1, "बक्सर": 1, "ठेकेदारसम्म": 1, "निकाल्न": 1, "वनभोज": 1, "माला": 1, "लगाउन": 1, "खुले": 1, "बाँड्न": 3, "तपाईंका": 1, "पीडा": 1, "गन्न": 2, "कुनै": 3, "समाजसेवा": 1, "जनसेवक": 1, "संस्था": 1, "व्यवस्थित": 2, "उद्योग": 1, "होली": 1, "वाइन": 1, "लठ्ठिएर": 1, "जहाज": 1, "काख": 1, "वामपन्थ": 2, "पत्री": 1, "मजदुर": 12, "रिमाल": 1, "बालुवाटार": 3, "जमकट्टेल": 1, "गाडी": 2, "सडक": 2, "संक्रमण": 2, "पार": 2, "स‌ंविधान": 1, "लाेकतन्त्र": 1, "पोलिँदै": 1, "कुरुप": 2, "दृश्य": 3, "भोक": 4, "लङमार्च": 1, "क्रान्ति": 2, "पुर्वाभास": 1, "पुनको": 1, "ठाउँ": 2, "पाहुना": 3, "भर्ती": 1, "गरियोस्": 3, "संसार": 4, "मान्यता": 1, "नदिए": 1, "प्रश्न": 10, "राखेर": 2, "अपराध": 6, "मेडिकल": 2, "घोटाला": 1, "उठाएर": 1, "सावधानीकालागि": 1, "बोलेर": 1, "यिन": 3, "ढकाल": 5, "गित": 1, "गाएनन्": 1, "आवश्यकता": 2, "मनु": 1, "मन्जिल": 1, "यसरी": 4, "बाहिर": 3, "निस्कन": 1, "हुन्न": 1, "बस्नुपर्छ": 1, "पारिजात": 2, "एकपल्ट": 1, "पछ्यौरा": 1, "लुकाउने": 2, "दुष्प्रयास": 1, "भट्मास": 1, "दिएर": 2, "साट्न": 1, "साँघुरो": 1, "भिरालो": 1, "काठमाडौंमा": 1, "पाइन": 1, "हिड्नु": 1, "अवस्था": 1, "हिडेका": 1, "कतिपय": 1, "कारण": 6, "हुनसक्छ": 1, "पर्यटन": 1, "योगेश": 1, "भट्टराई": 2, "युवा": 1, "तथा": 1, "गरिए": 2, "कुमारी": 2, "पठाउनु": 1, "हुन्छहोला": 1, "प्लेन": 2, "उडि": 1, "सीट": 1, "लगाऊ": 1, "कार्बाही": 1, "गरि": 7, "एयर": 1, "होस्टेस्स": 1, "उडाउ": 1, "पुगिन्छ": 1, "दिनरात": 2, "बिरुद्ध": 1, "अग्र": 1, "मोर्चा": 1, "थिए": 6, "कारबाही": 4, "भागिदार": 1, "दुर्गन्ध": 2, "फैलिए": 1, "झनै": 1, "योग्य": 1, "ठहरिए": 1, "पतित": 1, "नमुना": 1, "लायक": 2, "तिम्रा": 2, "गिद्दे": 1, "नजर": 1, "सकेन": 1, "गिद्द": 1, "भनियो": 2, "सिनो": 4, "तिमी": 9, "लुछ्दै": 1, "थियौ": 1, "टेकु": 2, "अस्पताल": 6, "सेरबहादुर": 1, "तिम्रो": 3, "स्वास्थ्यमन्त्री": 1, "भानुभक्त": 1, "ठाडो": 1, "पत्राचार": 1, "भुमि": 1, "निर्वाह": 1, "उसै": 1, "सजाय": 1, "दिनु": 1, "दुर्गन्धित": 1, "बदनाम": 2, "हुन्छौं": 2, "मसी": 2, "एउटा": 4, "उम्मेद्बार": 1, "थियो": 6, "सत्ताकालागि": 2, "रक्सी": 1, "मासु": 2, "बन्दोबस्ती": 1, "गरेनौँ": 1, "क्षेत्र": 3, "त्यसै": 4, "गर्दैनौं": 1, "नरोक": 1, "नछेक": 1, "सम्बोधन": 2, "गाउँ": 3, "जानु": 1, "क्वारेनटाईन": 1, "राख": 1, "नपार": 1, "हिँडेर": 1, "सिन्धुली": 1, "कलं": 1, "हरिसिद्धि": 1, "बौद्ध": 1, "बसाेबास": 1, "प्रहरी": 7, "रोकेर": 1, "ललितपुर": 1, "लुभु": 1, "प्रह": 1, "अंग्रेजीमा": 1, "उत्तरदायी": 1, "रेस्पोन्सिबल’": 2, "भनिन्छ": 1, "शब्द": 6, "बडो": 1, "अर्थ": 6, "दोहोर्‍याएर": 1, "प्रतिज्ञा": 2, "फेरिन्छु": 1, "भन्नु": 1, "धोका": 1, "खान्नँ": 1, "दोहोर्‍याउनु": 1, "मूल": 1, "दिशा": 1, "प्रदिप": 7, "गिरि": 9, "#अन्नपूर्ण": 7, "दैनिक": 12, "नाम": 4, "उनी": 13, "सहज": 1, "बुद्धि": 1, "उपहास": 1, "बनाइए": 1, "डाक्टरी": 1, "तर्साइए": 1, "गान्धी": 1, "हिन्द": 1, "वकिल": 1, "विश्वविद्यालय": 1, "विरोध": 1, "पढ्दा": 1, "प्रारम्भ": 1, "तिलमिलाए": 1, "थिएँ": 1, "बुझ्दै": 1, "दूरदर्शी": 1, "रुख": 1, "काटेर": 1, "चरनसकिएर": 1, "गाई": 1, "बाख्रालाई": 1, "गाउँले": 3, "बुझ्नसक्छन्": 1, "बुझ्न": 2, "नपाओस्": 1, "विश्वव्यवस्था": 1, "सक्रिय": 1, "निरन्तर": 1, "भनिए": 2, "बुझ्दैनौ": 1, "युगौँ": 1, "गर्दै": 4, "पाठ": 1, "पढाइँदै": 1, "ट्रम्प": 5, "पुटिन": 1, "निमित्त": 2, "समान": 1, "रूप": 1, "तैपनि": 1, "दोष": 1, "देखाउने": 1, "पंक्तिकार": 1, "शासनप्रणाली": 1, "प्रणाली": 2, "उदासीनता": 1, "नित्य": 2, "विनाश": 1, "नाइके": 1, "उदासीन": 1, "अर्": 2, "सवार": 2, "भोलि": 1, "टिकिरहनु": 1, "पहिलो": 2, "अगामी": 1, "जसरी": 2, "जित्नु": 1, "अर्को": 3, "सहरिया": 1, "बुझ्नै": 1, "अर्थमन्त्री": 1, "सहर": 2, "मजाक": 1, "संसद्": 1, "पेस": 1, "बनाउन": 1, "पाँच": 1, "उछिन्ने": 1, "गर्छन्": 2, "रहस्यमय": 1, "रहस्यमता": 1, "मानिस": 3, "सीमा": 1, "बताउँछ": 1, "तथाकथित": 1, "भ्रान्त": 1, "खतरनाक": 1, "अवधारणा": 1, "अज्ञानी": 1, "आत्महीन": 1, "थुप्रो": 1, "बालविवाह": 1, "उत्पीडन": 1, "सफासुग्घर": 1, "समझदारी": 1, "आधुनिकता": 1, "अन्धविश्वास": 1, "थप्दै": 1, "रहुन्जेल": 2, "भारत": 1, "अमेरिका": 3, "अन्यथा": 1, "हुनै": 1, "सक्दैन": 4, "यस्ता": 4, "सुन्न": 1, "विश्व": 1, "शक्तिशाली": 1, "सुपरिचत": 1, "डोनाल्ड": 1, "पर्छन्": 1, "हुल": 1, "एक्लै": 1, "पृथक्": 2, "सकिन्छ": 5, "केपी": 1, "सकिँदैन": 3, "वैज्ञानिक": 1, "चोट": 1, "बारम्बार": 2, "भन्दैछन्": 1, "सुन्ने": 2, "जीवनशैली": 1, "सुधार्‍यौँ": 1, "प्रकृति": 2, "बस्न": 1, "थाल्यौँ": 1, "सम्मान": 1, "गर्‍यौँ": 1, "विभीषिका": 2, "टर्नसक्छ": 1, "रुने": 1, "बबुरा": 1, "सुनि": 1, "मुहानअझै": 1, "पाए": 5, "जागरुक": 1, "जिम्मेवार": 1, "छैनौँ": 1, "अर्थात्": 1, "सन्": 1, "२०५०": 1, "गराउने": 1, "प्रयास": 1, "नगर्ने": 3, "मानव": 1, "लागिरहनलायक": 1, "हुँदैन": 2, "देखाउँछ": 1, "जीवन": 1, "क्षणभंगुर": 1, "कोही": 2, "जतै": 1, "व्यक्ति": 1, "अकस्मात्": 1, "सिकार": 1, "हुन्छन्": 1, "वृद्ध": 1, "बालक": 1, "मर्दैछन्": 2, "मर्दिनँ": 2, "प्रश्नचिह्न": 1, "लगाए": 1, "यक्ष": 1, "सम्झना": 1, "गराए": 1, "डुब्ने": 1, "माल्दिभ्स": 2, "डुब्छ": 1, "मेरो": 1, "डुब्दैन": 1, "मर्लान्": 1, "सामुन्ने": 1, "समाजवाद": 1, "मूलतः": 1, "प्रक्रिया": 1, "स्वतन्त्र": 2, "सशक्त": 1, "तदनुरूपश्रेष्ठतम": 1, "मनिस": 1, "खेलबाड": 1, "औँला": 1, "सकिने": 1, "बाँकी": 2, "भन्छन्": 1, "दशक": 2, "डुब्दैछ": 1, "करुण": 1, "पृष्ठभूमि": 1, "अध्यक्षद्वय": 1, "गर्दैैछन्": 1, "देखाउन": 2, "काँग्रेस": 1, "जंग्दिैछ": 1, "खुद्रा": 1, "भाषा": 1, "बुझाउन": 1, "प्रकट": 1, "विराट": 1, "विकराल": 1, "इतिहास": 3, "पृथक्छ": 1, "मानवजाति": 1, "निरीहता": 1, "उजागर": 1, "प्रदीप": 1, "चिन्ता": 2, "लखेटे": 1, "श्रमिक": 2, "सकस": 1, "लेखाइ": 1, "तीस": 1, "चालीसको": 1, "सीमित": 1, "लाग्दैन": 1, "वर्तमान": 1, "प्रतिरोधी": 1, "मसाल": 1, "बालेर": 1, "लाग्छन्": 1, "घरिघरि": 1, "आजै": 3, "कुरूपता": 1, "उचालिरहेछन्": 1, "देवकोटा": 1, "सभ्यता": 2, "नियामक": 1, "लोभ": 1, "चले": 1, "चल्न": 1, "उठाए": 1, "देशमा": 1, "अझै": 3, "बस्ने": 1, "गरौं": 2, "कार्यक्रम": 1, "बनाउँदा": 1, "बन्दुक": 1, "बोक्न": 1, "निम्ति": 1, "प्रयोजन": 1, "चुनाब": 1, "जितौं": 1, "लागी": 1, "लालबहादुर–लालकुमारी": 1, "अनुमोदन": 1, "गरियो": 1, "किमि": 1, "बलियोगरि": 1, "निर्माण": 1, "हुनकालागि": 1, "अवयब": 1, "श्रोत": 2, "माटो": 1, "नभएर": 4, "रुपि": 1, "कमजोर": 1, "भत्किन": 1, "पाइला": 1, "आमा": 5, "श्रद्धाञ्जली": 1, "बन्चित": 1, "हुन्छु": 1, "सोच्छु": 1, "टेस्ट": 1, "विश्वसनीयता": 1, "नेगेटिभ": 1, "देखिए": 1, "उदयपुर": 1, "जना": 3, "पिसिआर": 1, "पोजेटिभ": 1, "क्षति": 1, "बेहोर्नु": 1, "भर्खर": 1, "ललितपरको": 1, "विभिन्न": 1, "पैदलै": 2, "बल्खु": 1, "सोचुन": 1, "आँशु": 1, "राजमार्ग": 3, "सितिमिति": 1, "सिंहदरवार": 1, "ढोका": 1, "बन्द": 1, "सोलु": 1, "कैलाली": 1, "काठमाडौं": 1, "सुनसरी": 1, "हिँडिए": 1, "बिर्सिने": 1, "श्रमिकलाई": 1, "फर्कने": 1, "प्रबन्ध": 1, "गरौँ": 4, "#प्रदिप": 1, "बालुवाटारमा": 1, "निर्देशन": 1, "लकडाउन’": 1, "कडा": 1, "पार्नू": 1, "मौन": 1, "पागल": 5, "छौँ": 3, "बैरो": 1, "पागलपन": 1, "गिद्ध": 6, "धिक्कार": 3, "ओलीतन्त्र": 1, "राखिराखौँ": 1, "बाध्यकारी": 1, "अपिल": 1, "कांग्रेसी": 1, "कार्यकर्ता": 1, "बुझिदिए": 1, "राम्रो": 3, "हुनेथियो": 1, "सभापति": 2, "केहि": 2, "निर्देशनात्मक": 1, "लाभप्रद": 1, "हुनसक्थ्यो": 1, "पर्सि": 1, "प्रतिबद्धता": 2, "खारेज": 1, "गरिन्छ": 2, "गर्नेछन्": 1, "हेरौँला": 1, "सुनौँला": 1, "तिनी": 1, "कमोड": 1, "गरिदिने": 1, "सब्दकालागि": 1, "का‌ंग्रेसको": 1, "यिनी": 2, "समाजवाद’": 1, "उक्त": 1, "मानहानी": 1, "गएर": 1, "कानूनी": 1, "परो": 1, "हैकमी": 1, "राजसी": 1, "भनिदेउ": 1, "बग्ने": 1, "महाकाली": 1, "निधो": 1, "आफै": 1, "गछौं–": 1, "दिनहुं": 1, "भनेन": 1, "त्यहां": 1, "ग्रिनकार्ड": 1, "होल्डर": 1, "सहयोग": 2, "भनाैं": 1, "सधैं": 1, "यस्ताे": 1, "रहँदैन्": 1, "बाँचिएछ": 1, "देखिएला": 1, "खसाल्न": 1, "जाने": 1, "अघिल्लाे": 1, "अाफ्रनाे": 1, "टुइटर": 1, "हुँदाहुँदा": 1, "अनुसन्धान": 1, "कुट्यो": 1, "\"प्रहरी": 1, "साथी\"": 1, "बिरोध": 3, "निर्विकल्प": 1, "स्वीकृत": 1, "स्वास्थ्यकर्मी": 3, "कस्": 2, "सम्झिएर": 1, "आएका": 1, "निषेध": 1, "ल्याउन": 2, "पानीजहाज": 2, "रेल": 2, "ल्याउने": 1, "सानो": 1, "ट्वाईलेट": 2, "उद्घाटन": 2, "गर्दा": 1, "युग": 3, "प्रवेश": 2, "मौलिकता": 1, "छुन्थ्यो": 1, "थियौं": 1, "जिबन": 2, "गरिदिए": 1, "औषधि": 2, "बिपी": 1, "कतै": 1, "भाबुक": 1, "नजिक": 1, "राख्छ": 1, "अरुको": 1, "दुख": 1, "गराउछ": 1, "नकचरो": 1, "थेत्तरो": 1, "जल्लाद": 1, "बज्रस्वाँठ": 1, "हल्लुण‍ो": 1, "निच": 1, "सरदार": 1, "पत्रु": 1, "भुत्रो": 1, "दानापानी": 1, "देखियो": 1, "देख्नु": 1, "मजदूर": 1, "विपदमा": 1, "संसारभरि": 1, "गृहमन्त्रालय": 1, "सम्झन्छन्": 1, "यस्तै": 1, "विपत": 1, "सम्झिइन्छ": 1, "गृहमन्त्रीचाहिँ": 1, "खोकना": 1, "शुद्ध": 1, "पुल्चोक": 1, "ढुंगो": 1, "बोल्छ": 1, "गृहमन्त्री": 1, "बोल्दैनन्": 1, "कमिसनकालागि": 1, "मुटु": 1, "हिनता": 1, "परिवार": 1, "गर्थेंउ": 1, "किरिया": 1, "सिमाना": 2, "नसक्ने": 1, "गर्छौ": 1, "अाेलीतन्त्र": 1, "मुर्दावाद": 1, "साँझ": 1, "बिहान": 1, "झण्डै": 2, "लाख": 2, "सरकारी": 1, "खान्छन्": 1, "राशन": 1, "कार्ड": 1, "आवेदन": 1, "गरीबहरुलाई": 1, "बागबजार": 1, "लिबरल": 1, "बुर्जुवा": 1, "देख्दा": 1, "लज्जा": 1, "गरेछन्": 1, "समाजवादी": 1, "कमरेड": 1, "लिएर": 1, "फर्किए": 1, "गुमे": 1, "विश्वास": 2, "पुनः": 1, "अवसर": 1, "टरे": 1, "पोखिए": 1, "अाँशु": 1, "कहिल्यै": 1, "नसुक्ने": 1, "पोतिए": 1, "पतन": 2, "रहन्न": 1, "साथी": 2, "भेटियन": 1, "गुनासो": 1, "गर्नुभयको": 1, "खोजेर": 1, "आक्रोश": 1, "कुतन्त्र": 2, "निन्द्रा": 1, "लाग्दो": 1, "निदाउनु": 1, "सुत्ने": 2, "छाती": 1, "होलान्": 1, "जनमत": 1, "पुरा": 1, "हुँदैछ": 2, "खोइ": 1, "अाँसु": 2, "बिहिनता": 2, "गरेकोछ": 1, "अखवार": 1, "पढ्न": 1, "पाउनु": 1, "पिपिइ": 1, "कुट्दैछन्": 1, "भएन": 2, "निथ्रुक्क": 1, "मर्दा": 2, "खुल्दैन": 1, "काेराेना": 1, "जुध्ने": 1, "हदै": 1, "देखेर": 2, "गर्दैछ": 1, "उठ्दैथ्याे": 1, "गर्दैछु": 1, "ड्याङड्याङ": 1, "कुट्न": 1, "थाल्याे": 1, "टेके": 1, "पैताला": 1, "भावविभोर": 1, "बनोस्": 1, "भलाई": 1, "कामना": 1, "गरोस्": 2, "लाउँछ": 1, "मनमनै": 1, "सराप्छ": 1, "राज्यको": 1, "सुरक्षा": 3, "बसेर": 1, "हाक्दै": 1, "बनिदैन": 1, "कानुन": 1, "निर्ममता": 1, "हराए": 1, "केकालागि": 1, "बापत": 1, "कांग्रेस": 3, "निर्मम": 1, "जनस्वास्थ्य": 1, "संवेदन": 1, "दायित्वअन्तर्गत": 1, "राख्नु": 1, "अल्माआटा": 1, "सम्मेलन": 1, "मुद्दा": 1, "बोकेर": 1, "रुनु": 1, "विडम्बना": 1, "कोण": 1, "अपराधअन्तर्गत": 1, "पर्दछ": 1, "लौन": 3, "बोकि": 1, "रहेछौं": 1, "व्यबस्थापन": 1, "फटफटाइ": 1, "खुवाइरहेछन्": 1, "निःशुल्क": 1, "*कुरा": 1, "गद्दार": 1, "तक्मा": 1, "दिँदै": 1, "भौतिक": 1, "सफाइ": 1, "बोकेका": 1, "राम": 1, "झाँक्री": 4, "नौलो": 2, "कोरा": 1, "निस्के": 1, "सजिलो": 1, "सरकार’": 1, "पाइन्छ": 1, "दिनुहोस्": 1, "सहने": 1, "गणतान्त्रिक": 1, "नेपालकालागि": 1, "बयलगाडा": 2, "पुगिन्न": 1, "भन्थे": 1, "लवज": 1, "पाउँदैन": 1, "भनेनौँ": 1, "ठुलो": 1, "भुल": 1, "रह्यो": 1, "चुकाइ": 1, "रहेकाछौँ": 1, "ढिला": 1, "नगरी": 1, "सहिअर्थ": 1, "बाँच्नुपर्छ": 1, "चन्द्र": 1, "किशोर": 1, "लेख्नुहुन्छ": 1, "संकटले": 1, "खोजी": 1, "स्थापित": 1, "गराउँछ": 2, "यदाकदा": 1, "गरिनुपर्छ": 2, "उकुसमुकुस": 1, "सेफ्टी": 1, "भल्भ’": 1, "पाउँछ": 1, "अन्तर्य": 1, "चुप": 1, "रहनु": 1, "कुटपिट": 2, "छानबिन": 2, "चिकित्सक": 1, "माग": 3, "मन्त्रिपरिषद्को": 1, "सुक्न": 1, "नपाउँदै": 1, "२४सै": 1, "घन्टा": 2, "घन्टे": 1, "पिपिई": 3, "जोगाए": 1, "मण्डल": 1, "सिफ्ट": 2, "फेर्‍यो": 1, "एकजना": 1, "पुग्छ": 1, "हैन": 1, "सस्तो": 1, "जिम्मेबारी": 1, "गरन": 1, "श्रीमती": 1, "छोराछोरी": 1, "बर्दीया": 1, "जनुपरोस": 1, "अनी": 2, "त्रिवि": 1, "चिन्दैन": 1, "उनि": 2, "दुनियाँ": 1, "कल्पना": 1, "ग्यारेन्टी": 1, "कार्य": 1, "प्राथमिकिकरण": 1, "बहस": 2, "हिजो": 1, "कटौती": 1, "गरिन": 1, "संसद": 2, "बिकास": 1, "कोस": 1, "लानु": 1, "सुबिधा": 1, "अरब": 2, "सुकुम्": 1, "आयोग": 1, "पौडेल": 1, "गुँड": 1, "भत्कन्छ": 1, "स्वयं": 1, "संरक्षक": 1, "गर्छन": 1, "थकान": 1, "अनिश्चित": 1, "माध्यम": 1, "सम्भावना": 1, "रहन्छ": 1, "ढाट्ने": 1, "परिणाम": 1, "जानै": 1, "हुन्नथ्यो": 1, "तथापि": 1, "जाँच": 1, "गराउनु": 1, "बुद्धिमता": 1, "बने": 1, "ठहर्छ": 1, "गाँज्दा": 1, "होसनखुल्ने": 1, "मरणमापनी": 1, "नपाउने": 1, "बुझ्नु": 1, "गृह": 1, "हृदय": 1, "संन्त्रास": 1, "`आइसोलेसन´": 1, "कोमा": 1, "दार्चुला": 1, "जनप्रतिनिधि": 1, "सिडिओ": 1, "फोन": 1, "छोरा": 1, "फर्किन": 1, "दिन्छन्": 1, "यता": 1, "साना": 1, "भाइबहिनी": 1, "दाजु": 1, "आउनुहुन्छ": 1, "उहाँ": 2, "ल्याउनुहोस्": 1, "सयौं": 1, "किलोमिटर": 1, "लामो": 1, "मार्चपास": 1, "गरेजसरी": 1, "त्यसरी": 1, "हिँड्ने": 1, "दलित": 2, "पहाडी": 1, "गरिबी": 1, "डामिए": 1, "पीँधकामान्छे": 1, "भोट": 2, "हिसाब": 1, "सकिए": 1, "शितल": 1, "त्रिभुवन": 1, "विमानस्थल": 1, "रू१५को": 1, "भण्डारी": 1, "बिलकुल": 1, "भर्छु": 1, "कता": 1, "समाज": 1, "बिद्धिजिबी": 1, "तप्का": 1, "स्वर": 1, "भोकालाई": 1, "देख": 1, "सुन": 1, "आकाश": 1, "पर्खेर": 1, "भाड्ने": 1, "सोच्दो": 1, "टुहुरे": 1, "सम्झेँ": 1, "बसाईँ": 1, "हिड्ने": 1, "वस्ने": 1, "रुवाउँछ": 1, "लाखौँ": 1, "उजाड़": 1, "स्वर्ग": 1, "बोल्दिने": 1, "कोहि": 2, "कमि": 1, "तथ्य": 1, "आर्थिक": 1, "रोक्ने": 1, "बाबुराम": 1, "उठाउनु": 1, "आवश्यक": 1, "अपरिहार्य": 1, "भन्नुहुन्छ": 1, "प्रत्यक्ष": 2, "समानुपातिक": 1, "जनलोकपाल": 1, "राज्यद्वारा": 1, "उत्तम": 1, "विकल्प": 1, "लुट्न": 1, "लुट": 1, "सुरक्षाकर्मी": 1, "त्यस्तो": 1, "फिर्ता": 1, "बोलाएर": 1, "पठाइयोस्": 1, "नगर": 2, "समिति": 2, "नियमित": 1, "खुवाइ": 1, "न्यौपाने": 1, "पकाएर": 1, "प्याक": 1, "बताए": 1, "कोइराला": 1, "होईन": 2, "निजी": 1, "सम्पत्ती": 1, "माग्नेह": 1, "काेइराला": 1, "बिरामी": 1, "कुरूवा": 1, "बाँड्दै": 1, "अन्य": 1, "पक्कै": 1, "तुलनात्मक": 1, "सफलता": 1, "पाइ": 1, "समानता": 1, "बाँधिने": 1, "जाउँ": 1, "चुँडिन्छ": 1, "नजि": 1, "आउँ": 1, "गाँठो": 1, "शिक्षा": 1, "एकै": 1, "निम्त्याउनु": 1, "नारा": 2, "प्राप्त": 1, "दलाल": 1, "पुँजीपती": 1, "दास": 1, "बनायो": 1, "प्राण": 1, "रहेन": 1, "घोषणापत्र": 1, "भुट्ने": 1, "सञ्चारमाध्यमसँग": 1, "दूरी": 1, "बढाउन": 1, "अस्ति": 1, "रोज्ने": 1, "स्वतन्त्रता": 1, "संकेत": 1, "गर्दैछन्": 1, "अनुमान": 1, "निरंकुशता": 1, "उन्मुख": 1, "सेयरबजार": 1, "ओरालो": 1, "लाग्यो": 1, "अर्थतन्त्र": 1, "खस्कियो": 1, "सोच्नु": 1, "रामकुमारी": 1, "कम्ती": 1, "मुर्दा": 1, "हाल्लाउनु": 1, "प्रधानमन्त्रीको": 1, "सचिवालय": 1, "नेतृ": 1, "आधारहीन": 1, "महोदय": 1, "साब": 1, "लडाकु": 1, "रकम": 1, "हाक्काहाक्कि": 1, "खुल्लेआम": 1, "हजम": 1, "फाइल": 1, "छुँदैन": 1, "निगम": 1, "किन्दा": 1}